{
  "timestamp": "2025-09-08T21:37:00.356626",
  "ticker": "AAPL",
  "data_points": 2490,
  "latest_signal": {
    "date": "2025-09-08",
    "signal": "HOLD",
    "position": "FLAT",
    "phase_quadrant": "Quadrante 3 (Picco -> Discesa)",
    "phase_value": 0.9251649452389377,
    "oscillator_value": 12.26916,
    "signal_strength": 73.09022247555107,
    "confidence": "HIGH",
    "price": 237.88,
    "timestamp": "2025-09-08T21:36:59.028965"
  },
  "backtest_metrics": {
    "total_return_%": 86.65547693788751,
    "max_drawdown_%": 2.041994619661249,
    "sharpe_ratio": 1.4842406392787135,
    "sortino_ratio": 1.1927080206584535,
    "calmar_ratio": 10.817999752247148,
    "total_trades": 11,
    "win_rate_%": 81.81818181818183,
    "profit_factor": 29.946455172859313
  },
  "cycle_analysis": {
    "dominant_period": 126.0,
    "p_value": 0.0,
    "significant": "True"
  }
}